serve.py
insertokname_authlib-0.0.0.dist-info/METADATA
insertokname_authlib-0.0.0.dist-info/WHEEL
insertokname_authlib-0.0.0.dist-info/top_level.txt
insertokname_authlib-0.0.0.dist-info/RECORD
