Metadata-Version: 2.1
Name: insertokname-authlib
Version: 0.0.0
Author-email: Hsiaoming Yang <me@lepture.com>
License: BSD-3-Clause
Requires-Python: >=3.8
Requires-Dist: cryptography
